_geoip_geolite2/GeoLite2-City.mmdb
_geoip_geolite2/__init__.py
_geoip_geolite2/__pycache__/__init__.cpython-37.pyc
python_geoip_geolite2_yplan-2019.1224.dist-info/METADATA
python_geoip_geolite2_yplan-2019.1224.dist-info/WHEEL
python_geoip_geolite2_yplan-2019.1224.dist-info/top_level.txt
python_geoip_geolite2_yplan-2019.1224.dist-info/RECORD
