Metadata-Version: 2.1
Name: python-geoip-geolite2-yplan
Version: 2019.1224
Summary: Provides access to the geolite2 database.  This product includes GeoLite2 data created by MaxMind, available from https://www.maxmind.com/
Home-page: https://github.com/YPlan/python-geoip/tree/master/geolite2
Author: Armin Ronacher
Author-email: armin.ronacher@active-4.com
Maintainer: Thomas Grainger
Maintainer-email: python-geoip-geolite2-yplan@graingert.co.uk
License: UNKNOWN
Platform: UNKNOWN
Classifier: Programming Language :: Python
Classifier: Programming Language :: Python :: 2
Classifier: Programming Language :: Python :: 2.6
Classifier: Programming Language :: Python :: 2.7
Classifier: Programming Language :: Python :: 3
Classifier: Programming Language :: Python :: 3.3
Classifier: Programming Language :: Python :: 3.4
